aldryn_sso/__init__.py
aldryn_sso/admin.py
aldryn_sso/apps.py
aldryn_sso/forms.py
aldryn_sso/managers.py
aldryn_sso/middleware.py
aldryn_sso/models.py
aldryn_sso/sso.py
aldryn_sso/urls.py
aldryn_sso/urls_i18n.py
aldryn_sso/views.py
aldryn_sso/migrations/0001_initial.py
aldryn_sso/migrations/0002_auto_20161019_1953.py
aldryn_sso/migrations/0003_auto_20170528_1039.py
aldryn_sso/migrations/__init__.py
aldryn_sso/static/aldryn_sso/css/aldryn-sso/base.css
aldryn_sso/static/aldryn_sso/img/favicon.ico
aldryn_sso/static/aldryn_sso/img/logos/divio-blue.svg
aldryn_sso/templates/aldryn_sso/admin_non_staff.html
aldryn_sso/templates/aldryn_sso/base.html
aldryn_sso/templates/aldryn_sso/basicauth_auth_required.html
aldryn_sso/templates/aldryn_sso/create_user.html
aldryn_sso/templates/aldryn_sso/login_screen.html
aldryn_sso/templates/aldryn_sso/includes/localdev_login_form.html
aldryn_sso/templates/aldryn_sso/includes/login_form.html
aldryn_sso/templates/aldryn_sso/includes/sso_login_button.html
aldryn_sso/templates/aldryn_sso/logos/divio-black.png
aldryn_sso/templates/aldryn_sso/logos/divio-black.svg
aldryn_sso/templates/aldryn_sso/logos/divio-blue.svg
aldryn_sso/templates/aldryn_sso/logos/divio-white.png
aldryn_sso/templates/aldryn_sso/logos/divio-white.svg
aldryn_sso/templates/cms/toolbar/items/login.html
tests/__init__.py
tests/settings.py
tests/test_migrations.py
aldryn_sso-2.1.0.dist-info/LICENSE
aldryn_sso-2.1.0.dist-info/METADATA
aldryn_sso-2.1.0.dist-info/WHEEL
aldryn_sso-2.1.0.dist-info/top_level.txt
aldryn_sso-2.1.0.dist-info/RECORD
